fix_plugin_aws/__init__.py
fix_plugin_aws/access_edges.py
fix_plugin_aws/aws_client.py
fix_plugin_aws/collector.py
fix_plugin_aws/configuration.py
fix_plugin_aws/utils.py
fix_plugin_aws/cmd/__init__.py
fix_plugin_aws/resource/__init__.py
fix_plugin_aws/resource/acm.py
fix_plugin_aws/resource/amazonq.py
fix_plugin_aws/resource/apigateway.py
fix_plugin_aws/resource/athena.py
fix_plugin_aws/resource/autoscaling.py
fix_plugin_aws/resource/backup.py
fix_plugin_aws/resource/base.py
fix_plugin_aws/resource/bedrock.py
fix_plugin_aws/resource/cloudformation.py
fix_plugin_aws/resource/cloudfront.py
fix_plugin_aws/resource/cloudtrail.py
fix_plugin_aws/resource/cloudwatch.py
fix_plugin_aws/resource/cognito.py
fix_plugin_aws/resource/config.py
fix_plugin_aws/resource/dynamodb.py
fix_plugin_aws/resource/ec2.py
fix_plugin_aws/resource/ecr.py
fix_plugin_aws/resource/ecs.py
fix_plugin_aws/resource/efs.py
fix_plugin_aws/resource/eks.py
fix_plugin_aws/resource/elasticache.py
fix_plugin_aws/resource/elasticbeanstalk.py
fix_plugin_aws/resource/elb.py
fix_plugin_aws/resource/elbv2.py
fix_plugin_aws/resource/glacier.py
fix_plugin_aws/resource/guardduty.py
fix_plugin_aws/resource/iam.py
fix_plugin_aws/resource/inspector.py
fix_plugin_aws/resource/kinesis.py
fix_plugin_aws/resource/kms.py
fix_plugin_aws/resource/lambda_.py
fix_plugin_aws/resource/opensearch.py
fix_plugin_aws/resource/pricing.py
fix_plugin_aws/resource/rds.py
fix_plugin_aws/resource/redshift.py
fix_plugin_aws/resource/route53.py
fix_plugin_aws/resource/s3.py
fix_plugin_aws/resource/sagemaker.py
fix_plugin_aws/resource/scp.py
fix_plugin_aws/resource/secretsmanager.py
fix_plugin_aws/resource/service_quotas.py
fix_plugin_aws/resource/sns.py
fix_plugin_aws/resource/sqs.py
fix_plugin_aws/resource/ssm.py
fix_plugin_aws/resource/waf.py
test/__init__.py
test/acccess_edges_test.py
test/aws_client_test.py
test/collector_test.py
test/configuration_test.py
test/graphbuilder_test.py
test/test_utils.py
test/resources/__init__.py
fixinventory_plugin_aws-4.2.0.dist-info/METADATA
fixinventory_plugin_aws-4.2.0.dist-info/WHEEL
fixinventory_plugin_aws-4.2.0.dist-info/entry_points.txt
fixinventory_plugin_aws-4.2.0.dist-info/top_level.txt
fixinventory_plugin_aws-4.2.0.dist-info/RECORD
